MANIFEST.in
README.rst
setup.py
ckanext/__init__.py
ckanext/eurovoc/__init__.py
ckanext/eurovoc/plugin.py
ckanext/eurovoc/categories/categories_en.json
ckanext/eurovoc/categories/categories_se.json
ckanext/eurovoc/fanstatic/.gitignore
ckanext/eurovoc/public/.gitignore
ckanext/eurovoc/templates/.gitignore
ckanext/eurovoc/templates/package/snippets/additional_info.html
ckanext/eurovoc/templates/package/snippets/package_metadata_fields.html
ckanext/eurovoc/tests/__init__.py
ckanext/eurovoc/tests/test_plugin.py
ckanext_eurovoc.egg-info/PKG-INFO
ckanext_eurovoc.egg-info/SOURCES.txt
ckanext_eurovoc.egg-info/dependency_links.txt
ckanext_eurovoc.egg-info/entry_points.txt
ckanext_eurovoc.egg-info/top_level.txt