Metadata-Version: 1.0
Name: ckanext-eurovoc
Version: 0.0.7
Summary: Add Eurovoc categories to CKAN's dataset schema
Home-page: https://github.com/ckan/ckanext-eurovoc
Author: Brook Elgie
Author-email: brook.elgie@okfn.org
License: AGPL
Keywords: CKAN Eurovoc
Platform: UNKNOWN
